qumranica/__init__.py
qumranica/api_client.py
qumranica/configuration.py
qumranica/exceptions.py
qumranica/rest.py
qumranica/api/__init__.py
qumranica/api/artefact_api.py
qumranica/api/catalogue_api.py
qumranica/api/edition_api.py
qumranica/api/imaged_object_api.py
qumranica/api/roi_api.py
qumranica/api/sign_interpretation_api.py
qumranica/api/text_api.py
qumranica/api/user_api.py
qumranica/api/util_api.py
qumranica/models/__init__.py
qumranica/models/account_activation_request_dto.py
qumranica/models/admin_editor_request_dto.py
qumranica/models/admin_editor_request_list_dto.py
qumranica/models/artefact_data_dto.py
qumranica/models/artefact_data_list_dto.py
qumranica/models/artefact_dto.py
qumranica/models/artefact_group_dto.py
qumranica/models/artefact_group_list_dto.py
qumranica/models/artefact_list_dto.py
qumranica/models/artefact_text_fragment_match_dto.py
qumranica/models/artefact_text_fragment_match_list_dto.py
qumranica/models/attribute_dto.py
qumranica/models/attribute_list_dto.py
qumranica/models/attribute_value_dto.py
qumranica/models/batch_edit_roi_dto.py
qumranica/models/batch_edit_roi_response_dto.py
qumranica/models/batch_update_artefact_placement_dto.py
qumranica/models/batch_updated_artefact_transform_dto.py
qumranica/models/catalogue_match_dto.py
qumranica/models/catalogue_match_input_dto.py
qumranica/models/catalogue_match_list_dto.py
qumranica/models/character_shape_dto.py
qumranica/models/commentary_create_dto.py
qumranica/models/commentary_dto.py
qumranica/models/create_artefact_dto.py
qumranica/models/create_artefact_group_dto.py
qumranica/models/create_attribute_dto.py
qumranica/models/create_attribute_value_dto.py
qumranica/models/create_text_fragment_dto.py
qumranica/models/delete_dto.py
qumranica/models/delete_token_dto.py
qumranica/models/detailed_editor_rights_dto.py
qumranica/models/detailed_user_dto.py
qumranica/models/detailed_user_token_dto.py
qumranica/models/direction.py
qumranica/models/edition_copy_dto.py
qumranica-0.7.2.dist-info/METADATA
qumranica-0.7.2.dist-info/WHEEL
qumranica-0.7.2.dist-info/top_level.txt
qumranica-0.7.2.dist-info/RECORD
