Metadata-Version: 2.1
Name: qumranica
Version: 0.7.2
Summary: Qumranica API Python connector
Home-page: https://qumranica.org
Author: Bronson Brown-deVost
Author-email: bronsonbdevost@gmail.com
License: UNKNOWN
Keywords: OpenAPI,OpenAPI-Generator,Qumranica API
Platform: UNKNOWN
Requires-Dist: certifi
Requires-Dist: python-dateutil
Requires-Dist: six (>=1.10)
Requires-Dist: urllib3 (>=1.15)
